LAM-0.4.7.data/data/companion/ChannelPositionPlots.py
LAM-0.4.7.data/data/companion/ManualVectorPlots.py
LAM-0.4.7.data/data/companion/SubsetDataChannel.py
LAM-0.4.7.data/data/companion/combineSets.py
LAM-0.4.7.data/data/companion/rotator.py
LAM-0.4.7.data/data/companion/script_descriptions.txt
LAM-0.4.7.data/data/companion/split_dataset.py
LAM-0.4.7.data/data/docs/CommandLineArgs.txt
LAM-0.4.7.data/data/docs/LICENSE.md
LAM-0.4.7.data/data/docs/README.md
LAM-0.4.7.data/data/docs/UserManual_v0.4.3.pdf
LAM-0.4.7.data/data/img/lam.ico
src/__init__.py
src/analysis.py
src/border_detect.py
src/interface.py
src/logger.py
src/parse_cmds.py
src/plot.py
src/plotfuncs.py
src/process.py
src/redirect.py
src/run.py
src/settings.py
src/statsMWW.py
src/system.py
src/vector_loop.py
src/version.py
LAM-0.4.7.dist-info/LICENSE.md
LAM-0.4.7.dist-info/METADATA
LAM-0.4.7.dist-info/WHEEL
LAM-0.4.7.dist-info/entry_points.txt
LAM-0.4.7.dist-info/top_level.txt
LAM-0.4.7.dist-info/RECORD
