Metadata-Version: 2.1
Name: LAM
Version: 0.4.7
Summary: Linear Analysis of Midgut
Author: Arto I. Viitanen
Author-email: arto.viitanen@helsinki.fi
License: GPL-3.0 License
Project-URL: Project, https://github.com/hietakangas-laboratory/LAM
Project-URL: Bug Reports, https://github.com/hietakangas-laboratory/LAM/issues
Project-URL: Tutorial Videos, https://www.youtube.com/playlist?list=PLjv-8Gzxh3AynUtI3HaahU2oddMbDpgtx
Project-URL: Publication, https://doi.org/10.1016/j.crmeth.2021.100059
Project-URL: Research Group, https://www.helsinki.fi/en/researchgroups/nutrient-sensing
Keywords: biology,data analysis,image object data
Classifier: Development Status :: 5 - Production/Stable
Classifier: Intended Audience :: Science/Research
Classifier: Topic :: Scientific/Engineering :: Bio-Informatics
Classifier: Programming Language :: Python :: 3.7
Classifier: Programming Language :: Python :: 3.8
Classifier: Programming Language :: Python :: 3.9
Classifier: Programming Language :: Python :: 3.10
Classifier: Programming Language :: Python :: 3 :: Only
Requires-Python: <=3.11,>3.6
License-File: LICENSE.md
Requires-Dist: matplotlib >=3.1.3
Requires-Dist: numpy >=1.18.1
Requires-Dist: pandas >=1.1
Requires-Dist: pathlib2 >=2.3
Requires-Dist: scikit-image >=0.16.2
Requires-Dist: scikit-learn >=0.22.1
Requires-Dist: scipy >=1.4.1
Requires-Dist: seaborn >=0.11.0
Requires-Dist: shapely >=1.7.0
Requires-Dist: statsmodels >=0.11.0
